pytrombone/__init__.py
pytrombone/cache.py
pytrombone/util.py
pytrombone/wrapper.py
pytrombone-0.1.3.dist-info/LICENSE
pytrombone-0.1.3.dist-info/WHEEL
pytrombone-0.1.3.dist-info/METADATA
pytrombone-0.1.3.dist-info/RECORD
