Metadata-Version: 2.1
Name: pytrombone
Version: 0.1.3
Summary: Wrapper for the Trombone project
Home-page: https://github.com/ulaval-rs/pytrombone
License: BSD-3-Clause
Keywords: text
Author: Gabriel Couture
Author-email: gacou54@ulaval.ca
Requires-Python: >=3.7,<4.0
Classifier: License :: OSI Approved :: BSD License
Classifier: Programming Language :: Python :: 3
Classifier: Programming Language :: Python :: 3.10
Classifier: Programming Language :: Python :: 3.7
Classifier: Programming Language :: Python :: 3.8
Classifier: Programming Language :: Python :: 3.9
Requires-Dist: requests (>=2.26.0,<3.0.0)
